semi/__init__.py
semi/notch.py
semi/notch_plot.py
semi/wafer_edge_profile_template.py
semi/carbon_concentration/__init__.py
semi/carbon_concentration/carbon_fit.py
semi/carbon_concentration/carbon_fit_org.py
semi/carbon_concentration/carbon_report.py
semi/wafer_contour/__init__.py
semi/wafer_contour/flat.py
semi/wafer_contour/inner_circle.py
semi/wafer_contour/line_segment.py
semi/wafer_contour/notch.py
semi/wafer_contour/outer_circle.py
semi/wafer_contour/wafer_contour.py
semi/wafer_contour/wafer_contour_circle.py
semi/wafer_contour/wafer_contour_org.py
semi/wafer_edge/__init__.py
semi/wafer_edge/profile_template.py
tests/__init__.py
tests/test_carbon_fit.py
tests/test_carbon_report.py
semi-0.0.4.dist-info/LICENSE.rst
semi-0.0.4.dist-info/METADATA
semi-0.0.4.dist-info/WHEEL
semi-0.0.4.dist-info/top_level.txt
semi-0.0.4.dist-info/RECORD
