Metadata-Version: 2.1
Name: semi
Version: 0.0.4
Summary: SEMI international standards
Home-page: https://bitbucket.org/hirschbeutel/semi
Author: hirschbeutel
Author-email: hirschbeutel@gmail.com
License: MIT
Platform: UNKNOWN
